fame3r/__init__.py
fame3r/_cli.py
fame3r/_internal.py
fame3r/_nerdd.py
fame3r/descriptors.py
fame3r/score.py
fame3r/data/logo.svg
fame3r/data/logo_vienna.gif
fame3r/data/nerdd.yml
fame3r-2.0.0.dist-info/METADATA
fame3r-2.0.0.dist-info/WHEEL
fame3r-2.0.0.dist-info/entry_points.txt
fame3r-2.0.0.dist-info/licenses/LICENSE
fame3r-2.0.0.dist-info/RECORD
