Metadata-Version: 2.1
Name: fame3r
Version: 2.0.0
Summary: FAME3R: a re-implementation of the FAME3 model
Author-email: Roxane Jacob <roxane.axel.jacob@univie.ac.at>, Leo Gaskin <leo.gaskin@univie.ac.at>
License: MIT
License-File: LICENSE
Requires-Python: >=3.11
Requires-Dist: cdpkit==1.2.3
Requires-Dist: joblib==1.4.2
Requires-Dist: numpy>=2.3.2
Requires-Dist: scikit-learn>=1.5.1
Provides-Extra: cli
Requires-Dist: typer>=0.16.0; extra == 'cli'
Provides-Extra: nerdd
Requires-Dist: nerdd-link>=0.5.0; extra == 'nerdd'
Requires-Dist: nerdd-module>=0.3.42; extra == 'nerdd'
